tritise/__init__.py
tritise/cli.py
tritise/libtritise.py
tritise-0.1.1.dist-info/entry_points.txt
tritise-0.1.1.dist-info/LICENSE
tritise-0.1.1.dist-info/WHEEL
tritise-0.1.1.dist-info/METADATA
tritise-0.1.1.dist-info/RECORD
