Metadata-Version: 2.1
Name: tritise
Version: 0.1.1
Summary: A small python library to handle trivial time series in an SQLite database.
Home-page: https://gitlab.com/asmw/tritise
License: MIT
Author: asmw
Author-email: asmw@asmw.org
Requires-Python: >=3.7,<4.0
Classifier: License :: OSI Approved :: MIT License
Classifier: Programming Language :: Python :: 3
Classifier: Programming Language :: Python :: 3.7
Classifier: Programming Language :: Python :: 3.8
Requires-Dist: click (>=7.0,<8.0)
Requires-Dist: python-dateutil (>=2.8.1,<3.0.0)
Requires-Dist: sqlalchemy (>=1.3.12,<2.0.0)
